selenium_pinterest/__init__.py
selenium_pinterest/selenium_pinterest.py
selenium_pinterest/url_creator.py
selenium_pinterest-0.0.84.dist-info/METADATA
selenium_pinterest-0.0.84.dist-info/WHEEL
selenium_pinterest-0.0.84.dist-info/top_level.txt
selenium_pinterest-0.0.84.dist-info/RECORD
