Metadata-Version: 2.1
Name: selenium-pinterest
Version: 0.0.84
Summary: Selenium Pinterest helps you follow / unfollow / pin / post to Pinterest
Home-page: https://github.com/Zselter07/selenium-pinterest
Author: Pentek Zsolt
License: UNKNOWN
Platform: UNKNOWN
Classifier: Programming Language :: Python :: 3
Classifier: License :: OSI Approved :: MIT License
Classifier: Operating System :: OS Independent
Requires-Python: >=3.6
Requires-Dist: kcu
Requires-Dist: selenium-firefox
